llm_tools_yt_transcript.py
llm_tools_yt_transcript-0.1.dist-info/licenses/LICENSE
llm_tools_yt_transcript-0.1.dist-info/METADATA
llm_tools_yt_transcript-0.1.dist-info/WHEEL
llm_tools_yt_transcript-0.1.dist-info/entry_points.txt
llm_tools_yt_transcript-0.1.dist-info/top_level.txt
llm_tools_yt_transcript-0.1.dist-info/RECORD
