Metadata-Version: 2.4
Name: llm-tools-yt-transcript
Version: 0.1
Summary: Make YouTube transcripts available to llm
Author: Rupert Lloyd
License-Expression: Apache-2.0
Project-URL: Homepage, https://github.com/rupello/llm-tools-yt-transcript
Project-URL: Changelog, https://github.com/rupello/llm-tools-yt-transcript/releases
Project-URL: Issues, https://github.com/rupello/llm-tools-yt-transcript/issues
Project-URL: CI, https://github.com/rupello/llm-tools-yt-transcript/actions
Requires-Python: >=3.9
License-File: LICENSE
Requires-Dist: llm>=0.26
Requires-Dist: requests>=2.32.4
Requires-Dist: youtube-transcript-api>=1.1.1
Provides-Extra: test
Requires-Dist: pytest; extra == "test"
Requires-Dist: llm-echo>=0.3a1; extra == "test"
Dynamic: license-file
